readme_py/__init__.py
readme_py/elements/__init__.py
readme_py/elements/elements.py
readme_py/elements/styles.py
readme_py/elements/utils.py
readme_py/generator/__init__.py
readme_py/generator/generator.py
readme_py/structure/__init__.py
readme_py/structure/structure.py
readme_py-0.0.7.dist-info/LICENSE
readme_py-0.0.7.dist-info/METADATA
readme_py-0.0.7.dist-info/WHEEL
readme_py-0.0.7.dist-info/top_level.txt
readme_py-0.0.7.dist-info/RECORD
