Metadata-Version: 2.1
Name: readme-py
Version: 0.0.7
Summary: Python library to generate perfect READMEs
Home-page: https://github.com/kritibytes/readme-py
Author: kritibytes
Author-email: kritibytes@gmail.com
License: UNKNOWN
Platform: UNKNOWN
Classifier: Programming Language :: Python :: 3
Classifier: License :: OSI Approved :: MIT License
Classifier: Operating System :: OS Independent
Classifier: Topic :: Software Development
Classifier: Natural Language :: English
Requires-Python: >=3.6
License-File: LICENSE
